butiran/__init__.py
butiran/vect3.py
butiran-0.0.9.dist-info/LICENSE
butiran-0.0.9.dist-info/METADATA
butiran-0.0.9.dist-info/WHEEL
butiran-0.0.9.dist-info/top_level.txt
butiran-0.0.9.dist-info/RECORD
