Metadata-Version: 2.1
Name: butiran
Version: 0.0.9
Summary: Python package for simulation of grain-based system
Home-page: https://github.com/dudung/butiran-py
Author: Sparisoma Viridi
Author-email: <dudung@email.com>
License: UNKNOWN
Keywords: python,first package
Platform: UNKNOWN
Classifier: Development Status :: 3 - Alpha
Classifier: Intended Audience :: Education
Classifier: Programming Language :: Python :: 2
Classifier: Programming Language :: Python :: 3
Classifier: Operating System :: MacOS :: MacOS X
Classifier: Operating System :: Microsoft :: Windows
